chefkoch/__init__.py
chefkoch/__main__.py
chefkoch/recipe.py
chefkoch/retrievers.py
python_chefkoch-2.1.2.dist-info/METADATA
python_chefkoch-2.1.2.dist-info/WHEEL
python_chefkoch-2.1.2.dist-info/licenses/LICENSE
python_chefkoch-2.1.2.dist-info/RECORD
