Metadata-Version: 2.4
Name: python-chefkoch
Version: 2.1.2
Summary: Python library to retrieve information from chefkoch.de
License: MIT
License-File: LICENSE
Author: Moritz Enderle
Author-email: contact@moritzenderle.com
Requires-Python: >=3.8,<4.0
Classifier: License :: OSI Approved :: MIT License
Classifier: Programming Language :: Python :: 3
Classifier: Programming Language :: Python :: 3.8
Classifier: Programming Language :: Python :: 3.9
Classifier: Programming Language :: Python :: 3.10
Classifier: Programming Language :: Python :: 3.11
Classifier: Programming Language :: Python :: 3.12
Classifier: Programming Language :: Python :: 3.13
Classifier: Programming Language :: Python :: 3.14
Requires-Dist: beautifulsoup4 (>=4.12.3,<5.0.0)
Requires-Dist: isodate (>=0.6.1,<0.7.0)
Requires-Dist: requests (>=2.31.0,<3.0.0)
